detafs/__init__.py
detafs/core.py
detafs-0.1.4.dist-info/METADATA
detafs-0.1.4.dist-info/WHEEL
detafs-0.1.4.dist-info/top_level.txt
detafs-0.1.4.dist-info/RECORD
